{
  "project_info": {
    "project_number": "697807862169",
    "project_id": "interview-98091",
    "storage_bucket": "interview-98091.firebasestorage.app"
  },
  "client": [
    {
      "client_info": {
        "mobilesdk_app_id": "1:697807862169:android:99cbbffceafe5ac7de7b08",
        "android_client_info": {
          "package_name": "com.example.frappe_login_app"
        }
      },
      "oauth_client": [],
      "api_key": [
        {
          "current_key": "AIzaSyC-BQnM2TkwgW9xz_dmuYGo6pne055UcYc"
        }
      ],
      "services": {
        "appinvite_service": {
          "other_platform_oauth_client": []
        }
      }
    }
  ],
  "configuration_version": "1"
}